praxos_python/__init__.py
praxos_python/client.py
praxos_python/config.py
praxos_python/exceptions.py
praxos_python/utils.py
praxos_python/models/__init__.py
praxos_python/models/context.py
praxos_python/models/environment.py
praxos_python/models/ontology.py
praxos_python/models/source.py
praxos_python/types/__init__.py
praxos_python/types/message.py
praxos_python-0.5.0.dist-info/METADATA
praxos_python-0.5.0.dist-info/WHEEL
praxos_python-0.5.0.dist-info/licenses/LICENSE
praxos_python-0.5.0.dist-info/RECORD
