Metadata-Version: 2.4
Name: Praxos-python
Version: 0.5.0
Summary: Python SDK for Praxos with Intelligent Search and KG Enhancements
Author-email: Masoud Kermani Poor <masoud@praxos.ai>, Soheil Sadabadi <soheil@praxos.ai>
License-File: LICENSE
Requires-Dist: httpx
Requires-Dist: pydantic
